chatplotlib/__init__.py
chatplotlib/chatplotlibrc.toml
chatplotlib/client.py
chatplotlib/plotter.py
chatplotlib/session.py
docs/README.zh_cn.md
chatplotlib-0.1.1.dist-info/METADATA
chatplotlib-0.1.1.dist-info/WHEEL
chatplotlib-0.1.1.dist-info/RECORD
