Metadata-Version: 2.3
Name: chatplotlib
Version: 0.1.1
Summary: A Large Language Model Auxiliary Data Visualization Tool Based on Matplotlib
License: MIT
Author: wuyao1997
Author-email: wuyao1997@qq.com
Requires-Python: >=3.9
Classifier: License :: OSI Approved :: MIT License
Classifier: Programming Language :: Python :: 3
Classifier: Programming Language :: Python :: 3.9
Classifier: Programming Language :: Python :: 3.10
Classifier: Programming Language :: Python :: 3.11
Classifier: Programming Language :: Python :: 3.12
Classifier: Programming Language :: Python :: 3.13
Requires-Dist: matplotlib (>=3.8.0)
Requires-Dist: openai (>=1.54)
Requires-Dist: toml (>=0.10.0)
